Metadata-Version: 2.1
Name: setconfig
Version: 1.3.0
Summary: Multi-structure YAML config loader 🐍🔌
Home-page: https://github.com/abionics/setconfig
Author: Alex Ermolaev
Author-email: abionics.dev@gmail.com
License: MIT
Keywords: config yaml dataclass pydantic init
Classifier: Intended Audience :: Developers
Classifier: Intended Audience :: Education
Classifier: Intended Audience :: System Administrators
Classifier: License :: OSI Approved :: MIT License
Classifier: Operating System :: OS Independent
Classifier: Programming Language :: Python :: 3.10
Classifier: Programming Language :: Python :: 3.11
Classifier: Programming Language :: Python :: 3.12
Classifier: Topic :: System :: Installation/Setup
Classifier: Topic :: Software Development :: Libraries
Classifier: Topic :: Software Development :: Libraries :: Python Modules
Classifier: Typing :: Typed
License-File: LICENSE.txt
